{
  "id": "2020406138",
  "address": "17 Menzies Road, Marsfield NSW 2122",
  "price": "For Sale $2,100,000",
  "status": "active",
  "sold_price": null,
  "headline": null,
  "description": "Property Description\nEndless potential waiting to be unlocked, zoned for Epping Boys and Cheltenham Girls !\nA peaceful, north-west corner position within the catchment for Epping Boys High School and Cheltenham Girls High School offers a perfect opportunity for all buyers. Set with the privacy of a high-walled courtyard, this Mediterranean-style single-level home invites an ideal family-friendly footprint.\nOpening to two outdoor spaces, an air-conditioned lounge room extends through dining to family\nRead more",
  "bedrooms": "5",
  "bathrooms": "2",
  "parking": "4",
  "property_type": "House",
  "property_size": "575.4m²",
  "agent_name": null,
  "agent_phone": null,
  "image_urls": [
    "https://rimh2.domainstatic.com.au/ritsMn_NkiGgQscivE5CUt_s8jQ=/180x180/filters:format(webp):quality(85):no_upscale()/https://images.domain.com.au/img/31192/contact_1515128.jpeg?date=639021269611470000",
    "https://rimh2.domainstatic.com.au/4ZrtxwUh3K0rynpEMYuBoQcaMso=/filters:format(webp):quality(85):no_upscale()/https://images.domain.com.au/img/Agencys/31192/logo_31192.jpg?date=131698989628357989?date=639022894505248891",
    "https://rimh2.domainstatic.com.au/D7ATm32nkOulP8AnWdJenxu9XIw=/1680x720/filters:format(webp):quality(85)/2020406138_1_1_251107_034336-w2000-h1333",
    "https://rimh2.domainstatic.com.au/_a5woB4DK66tIDZU6_8Mpy73P98=/fit-in/1920x1080/filters:format(webp):quality(85):no_upscale()/2020406138_20_3_251107_034346-w7016-h4961",
    "https://rimh2.domainstatic.com.au/S5Qk40ogLEMqUL0S3mpCgrhYJ3c=/fit-in/1920x1080/filters:format(webp):quality(85):no_upscale()/2020406138_2_1_251107_034336-w2000-h1333",
    "https://rimh2.domainstatic.com.au/WmDukrqqMR_39ZtPW4Jta4EiQ5M=/fit-in/1920x1080/filters:format(webp):quality(85):no_upscale()/2020406138_3_1_251107_034336-w2000-h1333",
    "https://rimh2.domainstatic.com.au/ritsMn_NkiGgQscivE5CUt_s8jQ=/180x180/filters:format(webp):quality(85):no_upscale()/https://images.domain.com.au/img/31192/contact_1515128.jpeg?date=639021269611470000",
    "https://rimh2.domainstatic.com.au/4ZrtxwUh3K0rynpEMYuBoQcaMso=/filters:format(webp):quality(85):no_upscale()/https://images.domain.com.au/img/Agencys/31192/logo_31192.jpg?date=131698989628357989?date=639022894505248891",
    "https://s.domainstatic.com.au/fe-server-search-listings/master-6888/_next/static/media/domain-insight.21cf7f0d.svg"
  ],
  "url": "https://www.domain.com.au/2020406138"
}